azure/mgmt/oracledatabase/__init__.py
azure/mgmt/oracledatabase/_client.py
azure/mgmt/oracledatabase/_configuration.py
azure/mgmt/oracledatabase/_patch.py
azure/mgmt/oracledatabase/_validation.py
azure/mgmt/oracledatabase/_version.py
azure/mgmt/oracledatabase/py.typed
azure/mgmt/oracledatabase/_utils/__init__.py
azure/mgmt/oracledatabase/_utils/model_base.py
azure/mgmt/oracledatabase/_utils/serialization.py
azure/mgmt/oracledatabase/aio/__init__.py
azure/mgmt/oracledatabase/aio/_client.py
azure/mgmt/oracledatabase/aio/_configuration.py
azure/mgmt/oracledatabase/aio/_patch.py
azure/mgmt/oracledatabase/aio/operations/__init__.py
azure/mgmt/oracledatabase/aio/operations/_operations.py
azure/mgmt/oracledatabase/aio/operations/_patch.py
azure/mgmt/oracledatabase/models/__init__.py
azure/mgmt/oracledatabase/models/_enums.py
azure/mgmt/oracledatabase/models/_models.py
azure/mgmt/oracledatabase/models/_patch.py
azure/mgmt/oracledatabase/operations/__init__.py
azure/mgmt/oracledatabase/operations/_operations.py
azure/mgmt/oracledatabase/operations/_patch.py
azure_mgmt_oracledatabase-3.0.0.dist-info/licenses/LICENSE
azure_mgmt_oracledatabase-3.0.0.dist-info/METADATA
azure_mgmt_oracledatabase-3.0.0.dist-info/WHEEL
azure_mgmt_oracledatabase-3.0.0.dist-info/top_level.txt
azure_mgmt_oracledatabase-3.0.0.dist-info/RECORD
